BungBing26/__init__.py
BungBing26/calculator.py
BungBing26/eda.py
BungBing26-3.11.4.dist-info/LICENCE.txt
BungBing26-3.11.4.dist-info/METADATA
BungBing26-3.11.4.dist-info/WHEEL
BungBing26-3.11.4.dist-info/top_level.txt
BungBing26-3.11.4.dist-info/RECORD
